instapy_cli/__init__.py
instapy_cli/__main__.py
instapy_cli/cli.py
instapy_cli/media.py
instapy_cli-0.0.12.dist-info/LICENSE
instapy_cli-0.0.12.dist-info/METADATA
instapy_cli-0.0.12.dist-info/WHEEL
instapy_cli-0.0.12.dist-info/entry_points.txt
instapy_cli-0.0.12.dist-info/top_level.txt
instapy_cli-0.0.12.dist-info/RECORD
