Metadata-Version: 2.1
Name: instapy-cli
Version: 0.0.12
Summary: Python library and cli used to upload photo on Instagram. W/o a phone!
Home-page: https://github.com/b3nab/instapy-cli
Author: Benedetto Abbenanti
Author-email: benedetto.abbenanti@gmail.com
License: MIT
Keywords: instagram private upload api instapy instapy-cli instapycli
Platform: UNKNOWN
Classifier: Development Status :: 5 - Production/Stable
Classifier: Intended Audience :: Developers
Classifier: Environment :: Console
Classifier: License :: OSI Approved :: MIT License
Classifier: Programming Language :: Python :: 2
Classifier: Programming Language :: Python :: 2.6
Classifier: Programming Language :: Python :: 2.7
Classifier: Programming Language :: Python :: 3
Classifier: Programming Language :: Python :: 3.4
Classifier: Programming Language :: Python :: 3.5
Classifier: Programming Language :: Python :: 3.6
Classifier: Programming Language :: Python :: 3.7
